setup.py
django_oscar_mollie.egg-info/PKG-INFO
django_oscar_mollie.egg-info/SOURCES.txt
django_oscar_mollie.egg-info/dependency_links.txt
django_oscar_mollie.egg-info/pbr.json
django_oscar_mollie.egg-info/requires.txt
django_oscar_mollie.egg-info/top_level.txt
mollie_oscar/__init__.py
mollie_oscar/app.py
mollie_oscar/facade.py
mollie_oscar/urls.py
mollie_oscar/views.py